codeblueprints/__init__.py
codeblueprints/codeblueprints.py
codeblueprints-0.1.0.dist-info/AUTHORS.rst
codeblueprints-0.1.0.dist-info/LICENSE
codeblueprints-0.1.0.dist-info/METADATA
codeblueprints-0.1.0.dist-info/WHEEL
codeblueprints-0.1.0.dist-info/top_level.txt
codeblueprints-0.1.0.dist-info/RECORD
