Metadata-Version: 2.1
Name: codeblueprints
Version: 0.1.0
Summary: Automates code planning by mapping issues(softwares requirements) to actionable modifications in your codebase, preparing for future code generation.
Author-email: Liu Yong <13311102957@163.com>
Maintainer-email: Liu Yong <13311102957@163.com>
License: Apache Software License 2.0
Project-URL: bugs, https://github.com/esperyong/codeblueprints/issues
Project-URL: changelog, https://github.com/esperyong/codeblueprints/blob/master/changelog.md
Project-URL: homepage, https://github.com/esperyong/codeblueprints
License-File: LICENSE
License-File: AUTHORS.rst
Requires-Dist: typer
Provides-Extra: dev
Requires-Dist: coverage ; extra == 'dev'
Requires-Dist: mypy ; extra == 'dev'
Requires-Dist: pytest ; extra == 'dev'
Requires-Dist: ruff ; extra == 'dev'
